pipcryptmodV3/__init__.py
pipcryptmodV3-1.1.0.dist-info/METADATA
pipcryptmodV3-1.1.0.dist-info/WHEEL
pipcryptmodV3-1.1.0.dist-info/top_level.txt
pipcryptmodV3-1.1.0.dist-info/RECORD
