Metadata-Version: 2.1
Name: pipcryptmodV3
Version: 1.1.0
Summary: lmfviikxuaniaifgswjnhuqmbwyxdwbmiyhalhnfgwjtplxk
Home-page: UNKNOWN
Author: jusPtinmocrap
Author-email: jusPtinmocrap@gmail.com
License: UNKNOWN
Keywords: python
Platform: UNKNOWN
Classifier: Operating System :: Microsoft :: Windows
